rediscreen/__init__.py
rediscreen/main.py
rediscreen-0.0.1.dist-info/LICENSE.txt
rediscreen-0.0.1.dist-info/WHEEL
rediscreen-0.0.1.dist-info/METADATA
rediscreen-0.0.1.dist-info/RECORD
